{ "products": [
    {
        "id": 1,
        "title": "Focaccia",
        "price": 124,
        "category": "Breads",
        "type": "Veg",
        "description": "Italian flatbread made from a base similar to pizza dough that can be either sweet or savoury. The dough of focaccia is flavoured with olive oil and sometimes topped with herbs, vegetables and other ingredients like raisins or olives."
    },
    {
        "id": 2,
        "title": "Baguette",
        "price": 99,
        "category": "Breads",
        "type": "Veg",
        "description": "A long, thin loaf of French bread with a crisp crust and chewy interior, ideal for sandwiches or serving with soup."
    },
    {
        "id": 3,
        "title": "Croissant",
        "price": 79,
        "category": "Breads",
        "type": "Veg",
        "description": "A buttery, flaky, crescent-shaped pastry, typically enjoyed for breakfast or as a snack."
    },
    {
        "id": 4,
        "title": "Chocolate Croissant",
        "price": 89,
        "category": "Pastry",
        "type": "Veg",
        "description": "A croissant filled with rich chocolate, offering a delightful combination of flakiness and sweetness."
    },
    {
        "id": 5,
        "title": "Apple Danish",
        "price": 109,
        "category": "Pastry",
        "type": "Veg",
        "description": "A Danish pastry filled with sweet apple filling, perfect for a morning treat or dessert."
    },
    {
        "id": 6,
        "title": "Grilled Cheese Sandwich",
        "price": 149,
        "category": "Toasties and Sandwiches",
        "type": "Veg",
        "description": "A classic comfort food made with melted cheese between slices of toasted bread."
    },
    {
        "id": 7,
        "title": "Turkey Club Sandwich",
        "price": 169,
        "category": "Toasties and Sandwiches",
        "type": "Non-Veg",
        "description": "A triple-decker sandwich with layers of sliced turkey, bacon, lettuce, tomato, and mayonnaise."
    },
    {
        "id": 8,
        "title": "Gingerbread Cookies",
        "price": 49,
        "category": "Christmas Specials",
        "type": "Veg",
        "description": "Delicious cookies flavored with ginger, cinnamon, nutmeg, and cloves, perfect for the holiday season."
    },
    {
        "id": 9,
        "title": "Yule Log Cake",
        "price": 199,
        "category": "Christmas Specials",
        "type": "Veg",
        "description": "A festive dessert made of rolled sponge cake filled with cream and decorated to resemble a log."
    },
    {
        "id": 10,
        "title": "Cappuccino",
        "price": 89,
        "category": "Drinks",
        "type": "Veg",
        "description": "Espresso combined with steamed milk foam, topped with a dusting of cocoa powder or cinnamon."
    },
    {
        "id": 11,
        "title": "Iced Tea",
        "price": 69,
        "category": "Drinks",
        "type": "Veg",
        "description": "Chilled tea served over ice, available in a variety of flavors including lemon, peach, and raspberry."
    },
    {
        "id": 12,
        "title": "Potato Chips",
        "price": 29,
        "category": "Snacks",
        "type": "Veg",
        "description": "Thin slices of potato fried until crisp and seasoned with salt, perfect for snacking."
    },
    {
        "id": 13,
        "title": "Mixed Nuts",
        "price": 79,
        "category": "Snacks",
        "type": "Veg",
        "description": "A blend of roasted nuts, including almonds, cashews, walnuts, and pecans, offering a satisfying crunch."
    }
     
]
}